README.md
ev3devcontext.py
setup.py
ev3devcontext.egg-info/PKG-INFO
ev3devcontext.egg-info/SOURCES.txt
ev3devcontext.egg-info/dependency_links.txt
ev3devcontext.egg-info/requires.txt
ev3devcontext.egg-info/top_level.txt