Metadata-Version: 1.2
Name: ev3devcontext
Version: 0.36
Summary: using the ev3devcontext library your EV3 program can run in different contexts without the need to change a single line of code
Home-page: https://www.github.com/harcokuppens/thonny-ev3dev/wiki/ev3devcontext
Author: Harco Kuppens
Author-email: h.kuppens@cs.ru.nl
License: MIT
Keywords: IDE education programming EV3 mindstorms lego
Platform: Windows
Platform: macOS
Platform: Linux
Classifier: Environment :: MacOS X
Classifier: Environment :: Win32 (MS Windows)
Classifier: Environment :: X11 Applications
Classifier: Intended Audience :: Developers
Classifier: Intended Audience :: Education
Classifier: Intended Audience :: End Users/Desktop
Classifier: License :: Freeware
Classifier: License :: OSI Approved :: MIT License
Classifier: Natural Language :: English
Classifier: Operating System :: MacOS
Classifier: Operating System :: Microsoft :: Windows
Classifier: Operating System :: POSIX
Classifier: Operating System :: POSIX :: Linux
Classifier: Programming Language :: Python
Classifier: Programming Language :: Python :: 3
Classifier: Programming Language :: Python :: 3 :: Only
Classifier: Programming Language :: Python :: 3.4
Classifier: Programming Language :: Python :: 3.5
Classifier: Programming Language :: Python :: 3.6
Classifier: Topic :: Education
Classifier: Topic :: Software Development
Requires-Python: >=3.4
